best/__init__.py
best/integration/__init__.py
best/unit/__init__.py
best/unit/conftest.py
best/unit/test_glue_session.py
best/unit/test_glue_session_demo.py
best/unit/test_session_apis.py
awsscv-100.0.5.dist-info/LICENSE.txt
awsscv-100.0.5.dist-info/METADATA
awsscv-100.0.5.dist-info/WHEEL
awsscv-100.0.5.dist-info/top_level.txt
awsscv-100.0.5.dist-info/RECORD
